pytest_semantic/__init__.py
pytest_semantic/config.py
pytest_semantic/embeddings.py
pytest_semantic/exceptions.py
pytest_semantic/generator.py
pytest_semantic/matcher.py
pytest_semantic/plugin.py
pytest_semantic-0.1.0.dist-info/METADATA
pytest_semantic-0.1.0.dist-info/WHEEL
pytest_semantic-0.1.0.dist-info/entry_points.txt
pytest_semantic-0.1.0.dist-info/licenses/LICENSE
pytest_semantic-0.1.0.dist-info/RECORD
