Metadata-Version: 2.4
Name: pytest-semantic
Version: 0.1.0
Summary: A pytest plugin for testing LLM outputs using semantic similarity matching
Project-URL: Homepage, https://github.com/tombedor/pytest-semantic
Project-URL: Issues, https://github.com/tombedor/pytest-semantic/issues
Author-email: Tom Bedor <tombedor@gmail.com>
License-Expression: MIT
License-File: LICENSE
Classifier: Development Status :: 3 - Alpha
Classifier: Framework :: Pytest
Classifier: Intended Audience :: Developers
Classifier: Operating System :: OS Independent
Classifier: Programming Language :: Python :: 3
Classifier: Programming Language :: Python :: 3.9
Classifier: Programming Language :: Python :: 3.10
Classifier: Programming Language :: Python :: 3.11
Classifier: Programming Language :: Python :: 3.12
Classifier: Topic :: Software Development :: Testing
Requires-Python: >=3.9
Requires-Dist: numpy>=1.20.0
Requires-Dist: pytest>=7.0.0
Requires-Dist: sentence-transformers>=2.0.0
Provides-Extra: test
Requires-Dist: pytest-cov>=4.0.0; extra == 'test'
Requires-Dist: pytest>=7.0.0; extra == 'test'
